vtesrulings/__init__.py
vtesrulings/api.py
vtesrulings/db.py
vtesrulings/discord.py
vtesrulings/models.py
vtesrulings/proposal.py
vtesrulings/repository.py
vtesrulings/scraper.py
vtesrulings/utils.py
vtesrulings/static/dist/bootstrap-icons.3536be6d.woff2
vtesrulings/static/dist/bootstrap-icons.5b9cac4e.woff
vtesrulings/static/dist/css/layout.css
vtesrulings/static/dist/css/layout.css.map
vtesrulings/static/dist/js/admin.js
vtesrulings/static/dist/js/admin.js.map
vtesrulings/static/dist/js/groups.js
vtesrulings/static/dist/js/groups.js.map
vtesrulings/static/dist/js/index.js
vtesrulings/static/dist/js/index.js.map
vtesrulings/static/img/black-chantry-icon.webp
vtesrulings/static/img/favicon.ico
vtesrulings/templates/404.html
vtesrulings/templates/admin.html
vtesrulings/templates/groups.html
vtesrulings/templates/index.html
vtesrulings/templates/layout.html
vtes_rulings-0.9.dist-info/LICENSE
vtes_rulings-0.9.dist-info/METADATA
vtes_rulings-0.9.dist-info/WHEEL
vtes_rulings-0.9.dist-info/entry_points.txt
vtes_rulings-0.9.dist-info/top_level.txt
vtes_rulings-0.9.dist-info/RECORD
